[
  {
    "id": "1PJ83Q1XWWjgFABl0GSQd6O-QbO1VH8s9",
    "filename": "1.png",
    "post_time": 1775193270,
    "status": "partial",
    "success_accounts": [
      "Dentista Curioso"
    ]
  },
  {
    "id": "1A4dRGDw0dDbekaWCWrur3iI4ZDoiR74I",
    "filename": "5.png",
    "post_time": 1775247224,
    "status": "manual_success",
    "accounts": [
      "Dentista Curioso"
    ]
  },
  {
    "id": "1gQZMRc0YmtFDtUju_xjUv0P0jlo1gwZ6",
    "filename": "6.png",
    "post_time": 1775247389,
    "accounts": [
      "Dentista Curioso"
    ]
  }
]